{
  "generated_at": "2026-04-04T18:38:20Z",
  "repos": [
    {
      "label": "Fedora CoreOS",
      "namespace": "fedora",
      "repo": "fedora-coreos",
      "daily_stats": [
        {
          "date": "2026-01-02",
          "count": 41790
        },
        {
          "date": "2026-01-03",
          "count": 40980
        },
        {
          "date": "2026-01-04",
          "count": 41177
        },
        {
          "date": "2026-01-05",
          "count": 53388
        },
        {
          "date": "2026-01-06",
          "count": 45184
        },
        {
          "date": "2026-01-07",
          "count": 50411
        },
        {
          "date": "2026-01-08",
          "count": 54011
        },
        {
          "date": "2026-01-09",
          "count": 51061
        },
        {
          "date": "2026-01-10",
          "count": 47690
        },
        {
          "date": "2026-01-11",
          "count": 47437
        },
        {
          "date": "2026-01-12",
          "count": 49284
        },
        {
          "date": "2026-01-13",
          "count": 50404
        },
        {
          "date": "2026-01-14",
          "count": 49355
        },
        {
          "date": "2026-01-15",
          "count": 47290
        },
        {
          "date": "2026-01-16",
          "count": 49447
        },
        {
          "date": "2026-01-17",
          "count": 45110
        },
        {
          "date": "2026-01-18",
          "count": 46791
        },
        {
          "date": "2026-01-19",
          "count": 52552
        },
        {
          "date": "2026-01-20",
          "count": 48230
        },
        {
          "date": "2026-01-21",
          "count": 46110
        },
        {
          "date": "2026-01-22",
          "count": 53205
        },
        {
          "date": "2026-01-23",
          "count": 54279
        },
        {
          "date": "2026-01-24",
          "count": 48279
        },
        {
          "date": "2026-01-25",
          "count": 48973
        },
        {
          "date": "2026-01-26",
          "count": 48866
        },
        {
          "date": "2026-01-27",
          "count": 48428
        },
        {
          "date": "2026-01-28",
          "count": 46727
        },
        {
          "date": "2026-01-29",
          "count": 45353
        },
        {
          "date": "2026-01-30",
          "count": 44918
        },
        {
          "date": "2026-01-31",
          "count": 42357
        },
        {
          "date": "2026-02-01",
          "count": 41770
        },
        {
          "date": "2026-02-02",
          "count": 42899
        },
        {
          "date": "2026-02-03",
          "count": 43166
        },
        {
          "date": "2026-02-04",
          "count": 44656
        },
        {
          "date": "2026-02-05",
          "count": 49155
        },
        {
          "date": "2026-02-06",
          "count": 50128
        },
        {
          "date": "2026-02-07",
          "count": 42354
        },
        {
          "date": "2026-02-08",
          "count": 42783
        },
        {
          "date": "2026-02-09",
          "count": 43742
        },
        {
          "date": "2026-02-10",
          "count": 43895
        },
        {
          "date": "2026-02-11",
          "count": 43935
        },
        {
          "date": "2026-02-12",
          "count": 43775
        },
        {
          "date": "2026-02-13",
          "count": 41986
        },
        {
          "date": "2026-02-14",
          "count": 39167
        },
        {
          "date": "2026-02-15",
          "count": 39511
        },
        {
          "date": "2026-02-16",
          "count": 40212
        },
        {
          "date": "2026-02-17",
          "count": 40990
        },
        {
          "date": "2026-02-18",
          "count": 44130
        },
        {
          "date": "2026-02-19",
          "count": 40833
        },
        {
          "date": "2026-02-20",
          "count": 25724
        },
        {
          "date": "2026-02-21",
          "count": 13366
        },
        {
          "date": "2026-02-22",
          "count": 6174
        },
        {
          "date": "2026-02-23",
          "count": 38
        },
        {
          "date": "2026-02-24",
          "count": 0
        },
        {
          "date": "2026-02-25",
          "count": 0
        },
        {
          "date": "2026-02-26",
          "count": 42623
        },
        {
          "date": "2026-02-27",
          "count": 40800
        },
        {
          "date": "2026-02-28",
          "count": 40186
        },
        {
          "date": "2026-03-01",
          "count": 39670
        },
        {
          "date": "2026-03-02",
          "count": 42274
        },
        {
          "date": "2026-03-03",
          "count": 41612
        },
        {
          "date": "2026-03-04",
          "count": 44097
        },
        {
          "date": "2026-03-05",
          "count": 49147
        },
        {
          "date": "2026-03-06",
          "count": 50216
        },
        {
          "date": "2026-03-07",
          "count": 45915
        },
        {
          "date": "2026-03-08",
          "count": 46260
        },
        {
          "date": "2026-03-09",
          "count": 49040
        },
        {
          "date": "2026-03-10",
          "count": 45840
        },
        {
          "date": "2026-03-11",
          "count": 45922
        },
        {
          "date": "2026-03-12",
          "count": 43600
        },
        {
          "date": "2026-03-13",
          "count": 41964
        },
        {
          "date": "2026-03-14",
          "count": 40599
        },
        {
          "date": "2026-03-15",
          "count": 41164
        },
        {
          "date": "2026-03-16",
          "count": 44212
        },
        {
          "date": "2026-03-17",
          "count": 42495
        },
        {
          "date": "2026-03-18",
          "count": 44204
        },
        {
          "date": "2026-03-19",
          "count": 49532
        },
        {
          "date": "2026-03-20",
          "count": 51300
        },
        {
          "date": "2026-03-21",
          "count": 44779
        },
        {
          "date": "2026-03-22",
          "count": 43770
        },
        {
          "date": "2026-03-23",
          "count": 44715
        },
        {
          "date": "2026-03-24",
          "count": 43639
        },
        {
          "date": "2026-03-25",
          "count": 42107
        },
        {
          "date": "2026-03-26",
          "count": 41257
        },
        {
          "date": "2026-03-27",
          "count": 40410
        },
        {
          "date": "2026-03-28",
          "count": 36279
        },
        {
          "date": "2026-03-29",
          "count": 38082
        },
        {
          "date": "2026-03-30",
          "count": 36146
        },
        {
          "date": "2026-03-31",
          "count": 41907
        },
        {
          "date": "2026-04-01",
          "count": 41278
        },
        {
          "date": "2026-04-02",
          "count": 45559
        },
        {
          "date": "2026-04-03",
          "count": 48800
        }
      ],
      "streams": [
        {
          "name": "testing-devel",
          "last_modified": "Sat, 04 Apr 2026 12:38:48 -0000",
          "digest_short": "sha256:3c2bfdb43cdd",
          "arch_count": 4
        },
        {
          "name": "rawhide",
          "last_modified": "Sat, 04 Apr 2026 10:32:42 -0000",
          "digest_short": "sha256:7e9660a1c5a5",
          "arch_count": 4
        },
        {
          "name": "next-devel",
          "last_modified": "Thu, 02 Apr 2026 10:31:06 -0000",
          "digest_short": "sha256:3c90c5ba74d3",
          "arch_count": 4
        },
        {
          "name": "stable",
          "last_modified": "Wed, 01 Apr 2026 12:50:23 -0000",
          "digest_short": "sha256:a18cc8dcf65c",
          "arch_count": 4
        },
        {
          "name": "testing",
          "last_modified": "Wed, 01 Apr 2026 12:49:04 -0000",
          "digest_short": "sha256:985a64f300da",
          "arch_count": 4
        },
        {
          "name": "next",
          "last_modified": "Wed, 01 Apr 2026 12:45:52 -0000",
          "digest_short": "sha256:fef8393ea34b",
          "arch_count": 4
        },
        {
          "name": "branched",
          "last_modified": "Sun, 01 Mar 2026 20:42:00 -0000",
          "digest_short": "sha256:ef30880cadd9",
          "arch_count": 4
        }
      ],
      "pulls_7d": 288051,
      "pulls_30d": 1320138,
      "pulls_90d": 3832106,
      "avg_daily_7d": 41150,
      "avg_daily_30d": 44004,
      "latest_date": "2026-04-03",
      "latest_pulls": 48800
    },
    {
      "label": "Fedora bootc",
      "namespace": "fedora",
      "repo": "fedora-bootc",
      "daily_stats": [
        {
          "date": "2026-01-02",
          "count": 4156
        },
        {
          "date": "2026-01-03",
          "count": 3413
        },
        {
          "date": "2026-01-04",
          "count": 4337
        },
        {
          "date": "2026-01-05",
          "count": 5742
        },
        {
          "date": "2026-01-06",
          "count": 7153
        },
        {
          "date": "2026-01-07",
          "count": 8866
        },
        {
          "date": "2026-01-08",
          "count": 8855
        },
        {
          "date": "2026-01-09",
          "count": 7248
        },
        {
          "date": "2026-01-10",
          "count": 4759
        },
        {
          "date": "2026-01-11",
          "count": 5022
        },
        {
          "date": "2026-01-12",
          "count": 7424
        },
        {
          "date": "2026-01-13",
          "count": 9915
        },
        {
          "date": "2026-01-14",
          "count": 10282
        },
        {
          "date": "2026-01-15",
          "count": 9511
        },
        {
          "date": "2026-01-16",
          "count": 9191
        },
        {
          "date": "2026-01-17",
          "count": 4137
        },
        {
          "date": "2026-01-18",
          "count": 3858
        },
        {
          "date": "2026-01-19",
          "count": 7655
        },
        {
          "date": "2026-01-20",
          "count": 5169
        },
        {
          "date": "2026-01-21",
          "count": 6756
        },
        {
          "date": "2026-01-22",
          "count": 6831
        },
        {
          "date": "2026-01-23",
          "count": 7373
        },
        {
          "date": "2026-01-24",
          "count": 3515
        },
        {
          "date": "2026-01-25",
          "count": 4209
        },
        {
          "date": "2026-01-26",
          "count": 6168
        },
        {
          "date": "2026-01-27",
          "count": 6107
        },
        {
          "date": "2026-01-28",
          "count": 7340
        },
        {
          "date": "2026-01-29",
          "count": 9831
        },
        {
          "date": "2026-01-30",
          "count": 6947
        },
        {
          "date": "2026-01-31",
          "count": 5760
        },
        {
          "date": "2026-02-01",
          "count": 5913
        },
        {
          "date": "2026-02-02",
          "count": 6665
        },
        {
          "date": "2026-02-03",
          "count": 9300
        },
        {
          "date": "2026-02-04",
          "count": 6023
        },
        {
          "date": "2026-02-05",
          "count": 7541
        },
        {
          "date": "2026-02-06",
          "count": 9980
        },
        {
          "date": "2026-02-07",
          "count": 3600
        },
        {
          "date": "2026-02-08",
          "count": 4223
        },
        {
          "date": "2026-02-09",
          "count": 6224
        },
        {
          "date": "2026-02-10",
          "count": 6591
        },
        {
          "date": "2026-02-11",
          "count": 9190
        },
        {
          "date": "2026-02-12",
          "count": 9028
        },
        {
          "date": "2026-02-13",
          "count": 6029
        },
        {
          "date": "2026-02-14",
          "count": 4284
        },
        {
          "date": "2026-02-15",
          "count": 4381
        },
        {
          "date": "2026-02-16",
          "count": 6393
        },
        {
          "date": "2026-02-17",
          "count": 8336
        },
        {
          "date": "2026-02-18",
          "count": 7722
        },
        {
          "date": "2026-02-19",
          "count": 4140
        },
        {
          "date": "2026-02-20",
          "count": 2807
        },
        {
          "date": "2026-02-21",
          "count": 1212
        },
        {
          "date": "2026-02-22",
          "count": 787
        },
        {
          "date": "2026-02-23",
          "count": 178
        },
        {
          "date": "2026-02-24",
          "count": 0
        },
        {
          "date": "2026-02-25",
          "count": 0
        },
        {
          "date": "2026-02-26",
          "count": 14328
        },
        {
          "date": "2026-02-27",
          "count": 7724
        },
        {
          "date": "2026-02-28",
          "count": 3863
        },
        {
          "date": "2026-03-01",
          "count": 5739
        },
        {
          "date": "2026-03-02",
          "count": 11251
        },
        {
          "date": "2026-03-03",
          "count": 7091
        },
        {
          "date": "2026-03-04",
          "count": 6707
        },
        {
          "date": "2026-03-05",
          "count": 7192
        },
        {
          "date": "2026-03-06",
          "count": 8360
        },
        {
          "date": "2026-03-07",
          "count": 3578
        },
        {
          "date": "2026-03-08",
          "count": 3913
        },
        {
          "date": "2026-03-09",
          "count": 8380
        },
        {
          "date": "2026-03-10",
          "count": 7453
        },
        {
          "date": "2026-03-11",
          "count": 7679
        },
        {
          "date": "2026-03-12",
          "count": 7151
        },
        {
          "date": "2026-03-13",
          "count": 8145
        },
        {
          "date": "2026-03-14",
          "count": 4167
        },
        {
          "date": "2026-03-15",
          "count": 4594
        },
        {
          "date": "2026-03-16",
          "count": 10224
        },
        {
          "date": "2026-03-17",
          "count": 8427
        },
        {
          "date": "2026-03-18",
          "count": 6684
        },
        {
          "date": "2026-03-19",
          "count": 11279
        },
        {
          "date": "2026-03-20",
          "count": 10278
        },
        {
          "date": "2026-03-21",
          "count": 9697
        },
        {
          "date": "2026-03-22",
          "count": 4523
        },
        {
          "date": "2026-03-23",
          "count": 12439
        },
        {
          "date": "2026-03-24",
          "count": 10259
        },
        {
          "date": "2026-03-25",
          "count": 11092
        },
        {
          "date": "2026-03-26",
          "count": 13430
        },
        {
          "date": "2026-03-27",
          "count": 6746
        },
        {
          "date": "2026-03-28",
          "count": 5465
        },
        {
          "date": "2026-03-29",
          "count": 7516
        },
        {
          "date": "2026-03-30",
          "count": 11801
        },
        {
          "date": "2026-03-31",
          "count": 9660
        },
        {
          "date": "2026-04-01",
          "count": 9962
        },
        {
          "date": "2026-04-02",
          "count": 7434
        },
        {
          "date": "2026-04-03",
          "count": 7052
        }
      ],
      "streams": [
        {
          "name": "latest",
          "last_modified": "Sat, 04 Apr 2026 10:30:11 -0000",
          "digest_short": "sha256:6e924dcb8305",
          "arch_count": 4
        },
        {
          "name": "rawhide",
          "last_modified": "Wed, 01 Apr 2026 12:33:07 -0000",
          "digest_short": "sha256:c03d2f5e8bc5",
          "arch_count": 4
        }
      ],
      "pulls_7d": 58890,
      "pulls_30d": 244580,
      "pulls_90d": 621791,
      "avg_daily_7d": 8412,
      "avg_daily_30d": 8152,
      "latest_date": "2026-04-03",
      "latest_pulls": 7052
    }
  ],
  "total_pulls_7d": 346941,
  "total_pulls_30d": 1564718,
  "total_pulls_90d": 4453897,
  "combined_daily": [
    {
      "date": "2026-01-02",
      "count": 45946
    },
    {
      "date": "2026-01-03",
      "count": 44393
    },
    {
      "date": "2026-01-04",
      "count": 45514
    },
    {
      "date": "2026-01-05",
      "count": 59130
    },
    {
      "date": "2026-01-06",
      "count": 52337
    },
    {
      "date": "2026-01-07",
      "count": 59277
    },
    {
      "date": "2026-01-08",
      "count": 62866
    },
    {
      "date": "2026-01-09",
      "count": 58309
    },
    {
      "date": "2026-01-10",
      "count": 52449
    },
    {
      "date": "2026-01-11",
      "count": 52459
    },
    {
      "date": "2026-01-12",
      "count": 56708
    },
    {
      "date": "2026-01-13",
      "count": 60319
    },
    {
      "date": "2026-01-14",
      "count": 59637
    },
    {
      "date": "2026-01-15",
      "count": 56801
    },
    {
      "date": "2026-01-16",
      "count": 58638
    },
    {
      "date": "2026-01-17",
      "count": 49247
    },
    {
      "date": "2026-01-18",
      "count": 50649
    },
    {
      "date": "2026-01-19",
      "count": 60207
    },
    {
      "date": "2026-01-20",
      "count": 53399
    },
    {
      "date": "2026-01-21",
      "count": 52866
    },
    {
      "date": "2026-01-22",
      "count": 60036
    },
    {
      "date": "2026-01-23",
      "count": 61652
    },
    {
      "date": "2026-01-24",
      "count": 51794
    },
    {
      "date": "2026-01-25",
      "count": 53182
    },
    {
      "date": "2026-01-26",
      "count": 55034
    },
    {
      "date": "2026-01-27",
      "count": 54535
    },
    {
      "date": "2026-01-28",
      "count": 54067
    },
    {
      "date": "2026-01-29",
      "count": 55184
    },
    {
      "date": "2026-01-30",
      "count": 51865
    },
    {
      "date": "2026-01-31",
      "count": 48117
    },
    {
      "date": "2026-02-01",
      "count": 47683
    },
    {
      "date": "2026-02-02",
      "count": 49564
    },
    {
      "date": "2026-02-03",
      "count": 52466
    },
    {
      "date": "2026-02-04",
      "count": 50679
    },
    {
      "date": "2026-02-05",
      "count": 56696
    },
    {
      "date": "2026-02-06",
      "count": 60108
    },
    {
      "date": "2026-02-07",
      "count": 45954
    },
    {
      "date": "2026-02-08",
      "count": 47006
    },
    {
      "date": "2026-02-09",
      "count": 49966
    },
    {
      "date": "2026-02-10",
      "count": 50486
    },
    {
      "date": "2026-02-11",
      "count": 53125
    },
    {
      "date": "2026-02-12",
      "count": 52803
    },
    {
      "date": "2026-02-13",
      "count": 48015
    },
    {
      "date": "2026-02-14",
      "count": 43451
    },
    {
      "date": "2026-02-15",
      "count": 43892
    },
    {
      "date": "2026-02-16",
      "count": 46605
    },
    {
      "date": "2026-02-17",
      "count": 49326
    },
    {
      "date": "2026-02-18",
      "count": 51852
    },
    {
      "date": "2026-02-19",
      "count": 44973
    },
    {
      "date": "2026-02-20",
      "count": 28531
    },
    {
      "date": "2026-02-21",
      "count": 14578
    },
    {
      "date": "2026-02-22",
      "count": 6961
    },
    {
      "date": "2026-02-23",
      "count": 216
    },
    {
      "date": "2026-02-24",
      "count": 0
    },
    {
      "date": "2026-02-25",
      "count": 0
    },
    {
      "date": "2026-02-26",
      "count": 56951
    },
    {
      "date": "2026-02-27",
      "count": 48524
    },
    {
      "date": "2026-02-28",
      "count": 44049
    },
    {
      "date": "2026-03-01",
      "count": 45409
    },
    {
      "date": "2026-03-02",
      "count": 53525
    },
    {
      "date": "2026-03-03",
      "count": 48703
    },
    {
      "date": "2026-03-04",
      "count": 50804
    },
    {
      "date": "2026-03-05",
      "count": 56339
    },
    {
      "date": "2026-03-06",
      "count": 58576
    },
    {
      "date": "2026-03-07",
      "count": 49493
    },
    {
      "date": "2026-03-08",
      "count": 50173
    },
    {
      "date": "2026-03-09",
      "count": 57420
    },
    {
      "date": "2026-03-10",
      "count": 53293
    },
    {
      "date": "2026-03-11",
      "count": 53601
    },
    {
      "date": "2026-03-12",
      "count": 50751
    },
    {
      "date": "2026-03-13",
      "count": 50109
    },
    {
      "date": "2026-03-14",
      "count": 44766
    },
    {
      "date": "2026-03-15",
      "count": 45758
    },
    {
      "date": "2026-03-16",
      "count": 54436
    },
    {
      "date": "2026-03-17",
      "count": 50922
    },
    {
      "date": "2026-03-18",
      "count": 50888
    },
    {
      "date": "2026-03-19",
      "count": 60811
    },
    {
      "date": "2026-03-20",
      "count": 61578
    },
    {
      "date": "2026-03-21",
      "count": 54476
    },
    {
      "date": "2026-03-22",
      "count": 48293
    },
    {
      "date": "2026-03-23",
      "count": 57154
    },
    {
      "date": "2026-03-24",
      "count": 53898
    },
    {
      "date": "2026-03-25",
      "count": 53199
    },
    {
      "date": "2026-03-26",
      "count": 54687
    },
    {
      "date": "2026-03-27",
      "count": 47156
    },
    {
      "date": "2026-03-28",
      "count": 41744
    },
    {
      "date": "2026-03-29",
      "count": 45598
    },
    {
      "date": "2026-03-30",
      "count": 47947
    },
    {
      "date": "2026-03-31",
      "count": 51567
    },
    {
      "date": "2026-04-01",
      "count": 51240
    },
    {
      "date": "2026-04-02",
      "count": 52993
    },
    {
      "date": "2026-04-03",
      "count": 55852
    }
  ]
}